[{"confidence": 0.51, "label": "person", "bottomright": {"x": 1188, "y": 253}, "topleft": {"x": 238, "y": 7}}, {"confidence": 0.33, "label": "person", "bottomright": {"x": 884, "y": 231}, "topleft": {"x": 842, "y": 118}}, {"confidence": 0.41, "label": "person", "bottomright": {"x": 914, "y": 234}, "topleft": {"x": 870, "y": 96}}, {"confidence": 0.33, "label": "person", "bottomright": {"x": 191, "y": 263}, "topleft": {"x": 131, "y": 165}}, {"confidence": 0.49, "label": "person", "bottomright": {"x": 352, "y": 265}, "topleft": {"x": 301, "y": 143}}, {"confidence": 0.35, "label": "person", "bottomright": {"x": 527, "y": 292}, "topleft": {"x": 472, "y": 136}}, {"confidence": 0.57, "label": "person", "bottomright": {"x": 829, "y": 304}, "topleft": {"x": 780, "y": 175}}, {"confidence": 0.55, "label": "person", "bottomright": {"x": 997, "y": 408}, "topleft": {"x": 934, "y": 154}}, {"confidence": 0.43, "label": "person", "bottomright": {"x": 398, "y": 393}, "topleft": {"x": 314, "y": 234}}, {"confidence": 0.32, "label": "person", "bottomright": {"x": 468, "y": 380}, "topleft": {"x": 370, "y": 247}}, {"confidence": 0.55, "label": "person", "bottomright": {"x": 651, "y": 388}, "topleft": {"x": 574, "y": 233}}, {"confidence": 0.64, "label": "person", "bottomright": {"x": 1240, "y": 455}, "topleft": {"x": 1189, "y": 250}}, {"confidence": 0.45, "label": "person", "bottomright": {"x": 177, "y": 532}, "topleft": {"x": 56, "y": 343}}, {"confidence": 0.71, "label": "person", "bottomright": {"x": 536, "y": 580}, "topleft": {"x": 450, "y": 365}}, {"confidence": 0.33, "label": "person", "bottomright": {"x": 607, "y": 616}, "topleft": {"x": 531, "y": 560}}, {"confidence": 0.4, "label": "person", "bottomright": {"x": 1100, "y": 711}, "topleft": {"x": 1019, "y": 626}}, {"confidence": 0.38, "label": "person", "bottomright": {"x": 1094, "y": 719}, "topleft": {"x": 982, "y": 668}}, {"confidence": 0.36, "label": "person", "bottomright": {"x": 1248, "y": 715}, "topleft": {"x": 1158, "y": 659}}]