[{"topleft": {"y": 6, "x": 181}, "confidence": 0.42, "bottomright": {"y": 247, "x": 1232}, "label": "person"}, {"topleft": {"y": 120, "x": 990}, "confidence": 0.35, "bottomright": {"y": 214, "x": 1043}, "label": "person"}, {"topleft": {"y": 160, "x": 154}, "confidence": 0.36, "bottomright": {"y": 263, "x": 208}, "label": "person"}, {"topleft": {"y": 197, "x": 495}, "confidence": 0.63, "bottomright": {"y": 315, "x": 553}, "label": "person"}, {"topleft": {"y": 187, "x": 700}, "confidence": 0.44, "bottomright": {"y": 314, "x": 759}, "label": "person"}, {"topleft": {"y": 207, "x": 744}, "confidence": 0.51, "bottomright": {"y": 348, "x": 815}, "label": "person"}, {"topleft": {"y": 197, "x": 893}, "confidence": 0.51, "bottomright": {"y": 359, "x": 953}, "label": "person"}, {"topleft": {"y": 262, "x": 333}, "confidence": 0.51, "bottomright": {"y": 445, "x": 393}, "label": "person"}, {"topleft": {"y": 304, "x": 250}, "confidence": 0.42, "bottomright": {"y": 470, "x": 322}, "label": "person"}, {"topleft": {"y": 345, "x": 654}, "confidence": 0.34, "bottomright": {"y": 452, "x": 722}, "label": "person"}, {"topleft": {"y": 378, "x": 688}, "confidence": 0.34, "bottomright": {"y": 554, "x": 753}, "label": "person"}, {"topleft": {"y": 435, "x": 232}, "confidence": 0.37, "bottomright": {"y": 582, "x": 294}, "label": "person"}, {"topleft": {"y": 469, "x": 382}, "confidence": 0.67, "bottomright": {"y": 601, "x": 444}, "label": "person"}, {"topleft": {"y": 584, "x": 87}, "confidence": 0.37, "bottomright": {"y": 666, "x": 149}, "label": "person"}, {"topleft": {"y": 660, "x": 723}, "confidence": 0.31, "bottomright": {"y": 717, "x": 801}, "label": "person"}, {"topleft": {"y": 656, "x": 816}, "confidence": 0.34, "bottomright": {"y": 718, "x": 899}, "label": "person"}, {"topleft": {"y": 659, "x": 952}, "confidence": 0.54, "bottomright": {"y": 719, "x": 1036}, "label": "person"}]