[{"topleft": {"y": 6, "x": 162}, "confidence": 0.31, "bottomright": {"y": 253, "x": 1244}, "label": "person"}, {"topleft": {"y": 118, "x": 973}, "confidence": 0.37, "bottomright": {"y": 220, "x": 1009}, "label": "person"}, {"topleft": {"y": 128, "x": 896}, "confidence": 0.5, "bottomright": {"y": 272, "x": 956}, "label": "person"}, {"topleft": {"y": 179, "x": 123}, "confidence": 0.34, "bottomright": {"y": 300, "x": 183}, "label": "person"}, {"topleft": {"y": 198, "x": 775}, "confidence": 0.54, "bottomright": {"y": 317, "x": 826}, "label": "person"}, {"topleft": {"y": 223, "x": 608}, "confidence": 0.45, "bottomright": {"y": 345, "x": 675}, "label": "person"}, {"topleft": {"y": 208, "x": 579}, "confidence": 0.44, "bottomright": {"y": 442, "x": 668}, "label": "person"}, {"topleft": {"y": 243, "x": 528}, "confidence": 0.46, "bottomright": {"y": 469, "x": 613}, "label": "person"}, {"topleft": {"y": 315, "x": 255}, "confidence": 0.53, "bottomright": {"y": 477, "x": 310}, "label": "person"}, {"topleft": {"y": 342, "x": 160}, "confidence": 0.69, "bottomright": {"y": 524, "x": 225}, "label": "person"}, {"topleft": {"y": 393, "x": 720}, "confidence": 0.54, "bottomright": {"y": 543, "x": 790}, "label": "person"}, {"topleft": {"y": 412, "x": 833}, "confidence": 0.45, "bottomright": {"y": 590, "x": 935}, "label": "person"}, {"topleft": {"y": 481, "x": 379}, "confidence": 0.58, "bottomright": {"y": 607, "x": 441}, "label": "person"}, {"topleft": {"y": 581, "x": 64}, "confidence": 0.31, "bottomright": {"y": 663, "x": 131}, "label": "person"}, {"topleft": {"y": 658, "x": 811}, "confidence": 0.45, "bottomright": {"y": 718, "x": 895}, "label": "person"}, {"topleft": {"y": 656, "x": 936}, "confidence": 0.61, "bottomright": {"y": 718, "x": 1017}, "label": "person"}]