[{"confidence": 0.65, "label": "person", "topleft": {"y": 175, "x": 501}, "bottomright": {"y": 324, "x": 561}}, {"confidence": 0.63, "label": "person", "topleft": {"y": 214, "x": 925}, "bottomright": {"y": 370, "x": 979}}, {"confidence": 0.69, "label": "person", "topleft": {"y": 203, "x": 363}, "bottomright": {"y": 433, "x": 464}}, {"confidence": 0.77, "label": "person", "topleft": {"y": 243, "x": 1148}, "bottomright": {"y": 445, "x": 1233}}, {"confidence": 0.67, "label": "person", "topleft": {"y": 373, "x": 541}, "bottomright": {"y": 597, "x": 621}}]