[{"confidence": 0.61, "label": "person", "topleft": {"y": 201, "x": 586}, "bottomright": {"y": 340, "x": 648}}, {"confidence": 0.72, "label": "person", "topleft": {"y": 218, "x": 292}, "bottomright": {"y": 444, "x": 361}}, {"confidence": 0.83, "label": "person", "topleft": {"y": 217, "x": 415}, "bottomright": {"y": 450, "x": 513}}, {"confidence": 0.7, "label": "person", "topleft": {"y": 242, "x": 1137}, "bottomright": {"y": 462, "x": 1217}}, {"confidence": 0.73, "label": "person", "topleft": {"y": 310, "x": 28}, "bottomright": {"y": 544, "x": 131}}, {"confidence": 0.61, "label": "person", "topleft": {"y": 394, "x": 586}, "bottomright": {"y": 605, "x": 684}}]