[{"bottomright": {"x": 656, "y": 186}, "confidence": 0.07, "topleft": {"x": 626, "y": 159}, "label": "person"}, {"bottomright": {"x": 719, "y": 189}, "confidence": 0.06, "topleft": {"x": 692, "y": 156}, "label": "person"}, {"bottomright": {"x": 788, "y": 186}, "confidence": 0.07, "topleft": {"x": 761, "y": 152}, "label": "person"}, {"bottomright": {"x": 843, "y": 194}, "confidence": 0.08, "topleft": {"x": 812, "y": 149}, "label": "person"}, {"bottomright": {"x": 943, "y": 192}, "confidence": 0.05, "topleft": {"x": 903, "y": 159}, "label": "person"}, {"bottomright": {"x": 995, "y": 193}, "confidence": 0.1, "topleft": {"x": 958, "y": 152}, "label": "person"}, {"bottomright": {"x": 1061, "y": 200}, "confidence": 0.14, "topleft": {"x": 1023, "y": 150}, "label": "person"}, {"bottomright": {"x": 1182, "y": 190}, "confidence": 0.06, "topleft": {"x": 1146, "y": 156}, "label": "person"}, {"bottomright": {"x": 314, "y": 230}, "confidence": 0.06, "topleft": {"x": 288, "y": 195}, "label": "person"}, {"bottomright": {"x": 454, "y": 232}, "confidence": 0.09, "topleft": {"x": 420, "y": 197}, "label": "person"}, {"bottomright": {"x": 655, "y": 224}, "confidence": 0.05, "topleft": {"x": 627, "y": 192}, "label": "person"}, {"bottomright": {"x": 859, "y": 266}, "confidence": 0.05, "topleft": {"x": 813, "y": 156}, "label": "person"}, {"bottomright": {"x": 950, "y": 248}, "confidence": 0.09, "topleft": {"x": 902, "y": 167}, "label": "person"}, {"bottomright": {"x": 990, "y": 227}, "confidence": 0.06, "topleft": {"x": 958, "y": 186}, "label": "person"}, {"bottomright": {"x": 1061, "y": 232}, "confidence": 0.16, "topleft": {"x": 1024, "y": 184}, "label": "person"}, {"bottomright": {"x": 1125, "y": 231}, "confidence": 0.1, "topleft": {"x": 1092, "y": 184}, "label": "person"}, {"bottomright": {"x": 1142, "y": 258}, "confidence": 0.26, "topleft": {"x": 1085, "y": 171}, "label": "person"}, {"bottomright": {"x": 1186, "y": 229}, "confidence": 0.05, "topleft": {"x": 1154, "y": 186}, "label": "person"}, {"bottomright": {"x": 1198, "y": 257}, "confidence": 0.15, "topleft": {"x": 1139, "y": 170}, "label": "person"}, {"bottomright": {"x": 264, "y": 267}, "confidence": 0.09, "topleft": {"x": 230, "y": 225}, "label": "person"}, {"bottomright": {"x": 262, "y": 294}, "confidence": 0.08, "topleft": {"x": 209, "y": 211}, "label": "person"}, {"bottomright": {"x": 314, "y": 266}, "confidence": 0.1, "topleft": {"x": 282, "y": 222}, "label": "person"}, {"bottomright": {"x": 330, "y": 294}, "confidence": 0.18, "topleft": {"x": 279, "y": 206}, "label": "person"}, {"bottomright": {"x": 382, "y": 269}, "confidence": 0.09, "topleft": {"x": 353, "y": 218}, "label": "person"}, {"bottomright": {"x": 392, "y": 299}, "confidence": 0.35, "topleft": {"x": 345, "y": 205}, "label": "person"}, {"bottomright": {"x": 446, "y": 267}, "confidence": 0.12, "topleft": {"x": 411, "y": 220}, "label": "person"}, {"bottomright": {"x": 446, "y": 295}, "confidence": 0.4, "topleft": {"x": 396, "y": 203}, "label": "person"}, {"bottomright": {"x": 525, "y": 295}, "confidence": 0.08, "topleft": {"x": 470, "y": 195}, "label": "person"}, {"bottomright": {"x": 723, "y": 268}, "confidence": 0.09, "topleft": {"x": 692, "y": 221}, "label": "person"}, {"bottomright": {"x": 742, "y": 289}, "confidence": 0.06, "topleft": {"x": 694, "y": 198}, "label": "person"}, {"bottomright": {"x": 806, "y": 305}, "confidence": 0.19, "topleft": {"x": 758, "y": 194}, "label": "person"}, {"bottomright": {"x": 878, "y": 283}, "confidence": 0.22, "topleft": {"x": 830, "y": 198}, "label": "person"}, {"bottomright": {"x": 942, "y": 286}, "confidence": 0.05, "topleft": {"x": 895, "y": 207}, "label": "person"}, {"bottomright": {"x": 1006, "y": 300}, "confidence": 0.41, "topleft": {"x": 957, "y": 196}, "label": "person"}, {"bottomright": {"x": 1074, "y": 297}, "confidence": 0.2, "topleft": {"x": 1023, "y": 204}, "label": "person"}, {"bottomright": {"x": 1212, "y": 315}, "confidence": 0.2, "topleft": {"x": 1148, "y": 180}, "label": "person"}, {"bottomright": {"x": 74, "y": 328}, "confidence": 0.22, "topleft": {"x": 12, "y": 234}, "label": "person"}, {"bottomright": {"x": 106, "y": 327}, "confidence": 0.15, "topleft": {"x": 48, "y": 234}, "label": "person"}, {"bottomright": {"x": 219, "y": 336}, "confidence": 0.19, "topleft": {"x": 163, "y": 237}, "label": "person"}, {"bottomright": {"x": 251, "y": 341}, "confidence": 0.32, "topleft": {"x": 197, "y": 230}, "label": "person"}, {"bottomright": {"x": 315, "y": 327}, "confidence": 0.15, "topleft": {"x": 258, "y": 236}, "label": "person"}, {"bottomright": {"x": 648, "y": 361}, "confidence": 0.6, "topleft": {"x": 585, "y": 191}, "label": "person"}, {"bottomright": {"x": 779, "y": 360}, "confidence": 0.26, "topleft": {"x": 725, "y": 196}, "label": "person"}, {"bottomright": {"x": 1151, "y": 334}, "confidence": 0.08, "topleft": {"x": 1095, "y": 220}, "label": "person"}, {"bottomright": {"x": 1223, "y": 394}, "confidence": 0.09, "topleft": {"x": 1121, "y": 173}, "label": "person"}, {"bottomright": {"x": 306, "y": 353}, "confidence": 0.18, "topleft": {"x": 245, "y": 285}, "label": "person"}, {"bottomright": {"x": 753, "y": 397}, "confidence": 0.56, "topleft": {"x": 700, "y": 235}, "label": "person"}, {"bottomright": {"x": 1261, "y": 404}, "confidence": 0.64, "topleft": {"x": 1180, "y": 236}, "label": "person"}, {"bottomright": {"x": 414, "y": 438}, "confidence": 0.45, "topleft": {"x": 364, "y": 283}, "label": "person"}, {"bottomright": {"x": 431, "y": 466}, "confidence": 0.05, "topleft": {"x": 339, "y": 247}, "label": "person"}, {"bottomright": {"x": 485, "y": 441}, "confidence": 0.45, "topleft": {"x": 408, "y": 281}, "label": "person"}, {"bottomright": {"x": 552, "y": 457}, "confidence": 0.42, "topleft": {"x": 487, "y": 274}, "label": "person"}, {"bottomright": {"x": 1133, "y": 613}, "confidence": 0.38, "topleft": {"x": 130, "y": 102}, "label": "person"}, {"bottomright": {"x": 31, "y": 425}, "confidence": 0.07, "topleft": {"x": 3, "y": 373}, "label": "person"}, {"bottomright": {"x": 46, "y": 461}, "confidence": 0.15, "topleft": {"x": 3, "y": 342}, "label": "person"}, {"bottomright": {"x": 567, "y": 458}, "confidence": 0.17, "topleft": {"x": 518, "y": 318}, "label": "person"}, {"bottomright": {"x": 1005, "y": 502}, "confidence": 0.68, "topleft": {"x": 943, "y": 338}, "label": "person"}, {"bottomright": {"x": 67, "y": 674}, "confidence": 0.06, "topleft": {"x": 0, "y": 347}, "label": "person"}, {"bottomright": {"x": 299, "y": 588}, "confidence": 0.4, "topleft": {"x": 217, "y": 430}, "label": "person"}, {"bottomright": {"x": 593, "y": 593}, "confidence": 0.41, "topleft": {"x": 525, "y": 452}, "label": "person"}, {"bottomright": {"x": 413, "y": 599}, "confidence": 0.09, "topleft": {"x": 318, "y": 553}, "label": "tennis racket"}, {"bottomright": {"x": 50, "y": 650}, "confidence": 0.05, "topleft": {"x": 15, "y": 607}, "label": "person"}, {"bottomright": {"x": 76, "y": 667}, "confidence": 0.08, "topleft": {"x": 11, "y": 595}, "label": "person"}, {"bottomright": {"x": 115, "y": 666}, "confidence": 0.07, "topleft": {"x": 52, "y": 595}, "label": "person"}, {"bottomright": {"x": 199, "y": 647}, "confidence": 0.09, "topleft": {"x": 160, "y": 605}, "label": "person"}, {"bottomright": {"x": 205, "y": 665}, "confidence": 0.06, "topleft": {"x": 137, "y": 595}, "label": "person"}, {"bottomright": {"x": 80, "y": 715}, "confidence": 0.13, "topleft": {"x": 7, "y": 618}, "label": "person"}, {"bottomright": {"x": 146, "y": 719}, "confidence": 0.19, "topleft": {"x": 76, "y": 618}, "label": "person"}, {"bottomright": {"x": 193, "y": 708}, "confidence": 0.05, "topleft": {"x": 132, "y": 626}, "label": "person"}, {"bottomright": {"x": 253, "y": 685}, "confidence": 0.05, "topleft": {"x": 212, "y": 641}, "label": "person"}, {"bottomright": {"x": 417, "y": 705}, "confidence": 0.16, "topleft": {"x": 348, "y": 642}, "label": "person"}, {"bottomright": {"x": 187, "y": 714}, "confidence": 0.07, "topleft": {"x": 146, "y": 676}, "label": "person"}, {"bottomright": {"x": 267, "y": 713}, "confidence": 0.07, "topleft": {"x": 218, "y": 682}, "label": "person"}, {"bottomright": {"x": 268, "y": 719}, "confidence": 0.17, "topleft": {"x": 180, "y": 667}, "label": "person"}, {"bottomright": {"x": 325, "y": 714}, "confidence": 0.11, "topleft": {"x": 272, "y": 684}, "label": "person"}, {"bottomright": {"x": 407, "y": 714}, "confidence": 0.13, "topleft": {"x": 346, "y": 686}, "label": "person"}, {"bottomright": {"x": 472, "y": 712}, "confidence": 0.12, "topleft": {"x": 414, "y": 687}, "label": "person"}, {"bottomright": {"x": 500, "y": 718}, "confidence": 0.16, "topleft": {"x": 408, "y": 672}, "label": "person"}, {"bottomright": {"x": 540, "y": 715}, "confidence": 0.2, "topleft": {"x": 480, "y": 680}, "label": "person"}, {"bottomright": {"x": 601, "y": 719}, "confidence": 0.08, "topleft": {"x": 543, "y": 689}, "label": "person"}, {"bottomright": {"x": 618, "y": 716}, "confidence": 0.13, "topleft": {"x": 538, "y": 666}, "label": "person"}, {"bottomright": {"x": 690, "y": 719}, "confidence": 0.45, "topleft": {"x": 602, "y": 659}, "label": "person"}, {"bottomright": {"x": 1078, "y": 718}, "confidence": 0.06, "topleft": {"x": 188, "y": 664}, "label": "person"}, {"bottomright": {"x": 736, "y": 718}, "confidence": 0.24, "topleft": {"x": 690, "y": 678}, "label": "person"}, {"bottomright": {"x": 796, "y": 719}, "confidence": 0.25, "topleft": {"x": 747, "y": 685}, "label": "person"}, {"bottomright": {"x": 819, "y": 719}, "confidence": 0.19, "topleft": {"x": 726, "y": 675}, "label": "person"}, {"bottomright": {"x": 854, "y": 719}, "confidence": 0.22, "topleft": {"x": 816, "y": 694}, "label": "person"}, {"bottomright": {"x": 917, "y": 719}, "confidence": 0.13, "topleft": {"x": 880, "y": 697}, "label": "person"}, {"bottomright": {"x": 996, "y": 719}, "confidence": 0.27, "topleft": {"x": 953, "y": 702}, "label": "person"}, {"bottomright": {"x": 1062, "y": 719}, "confidence": 0.28, "topleft": {"x": 1015, "y": 705}, "label": "person"}, {"bottomright": {"x": 1132, "y": 719}, "confidence": 0.15, "topleft": {"x": 1091, "y": 710}, "label": "person"}, {"bottomright": {"x": 306, "y": 347}, "confidence": 0.09, "topleft": {"x": 255, "y": 309}, "label": "backpack"}, {"bottomright": {"x": 197, "y": 303}, "confidence": 0.05, "topleft": {"x": 166, "y": 264}, "label": "handbag"}, {"bottomright": {"x": 728, "y": 330}, "confidence": 0.07, "topleft": {"x": 704, "y": 301}, "label": "tennis racket"}, {"bottomright": {"x": 1203, "y": 378}, "confidence": 0.14, "topleft": {"x": 1173, "y": 349}, "label": "tennis racket"}, {"bottomright": {"x": 1001, "y": 151}, "confidence": 0.06, "topleft": {"x": 958, "y": 116}, "label": "chair"}, {"bottomright": {"x": 1207, "y": 326}, "confidence": 0.1, "topleft": {"x": 334, "y": 13}, "label": "chair"}, {"bottomright": {"x": 935, "y": 224}, "confidence": 0.07, "topleft": {"x": 900, "y": 188}, "label": "chair"}, {"bottomright": {"x": 922, "y": 269}, "confidence": 0.07, "topleft": {"x": 895, "y": 228}, "label": "chair"}, {"bottomright": {"x": 1061, "y": 260}, "confidence": 0.09, "topleft": {"x": 1031, "y": 223}, "label": "chair"}, {"bottomright": {"x": 995, "y": 297}, "confidence": 0.12, "topleft": {"x": 964, "y": 247}, "label": "chair"}, {"bottomright": {"x": 1062, "y": 294}, "confidence": 0.08, "topleft": {"x": 1031, "y": 256}, "label": "chair"}, {"bottomright": {"x": 1089, "y": 303}, "confidence": 0.08, "topleft": {"x": 1015, "y": 241}, "label": "chair"}]