[{"label": "person", "bottomright": {"x": 589, "y": 75}, "confidence": 0.06, "topleft": {"x": 554, "y": 39}}, {"label": "person", "bottomright": {"x": 314, "y": 112}, "confidence": 0.06, "topleft": {"x": 278, "y": 73}}, {"label": "person", "bottomright": {"x": 388, "y": 114}, "confidence": 0.06, "topleft": {"x": 354, "y": 78}}, {"label": "person", "bottomright": {"x": 657, "y": 116}, "confidence": 0.07, "topleft": {"x": 621, "y": 70}}, {"label": "person", "bottomright": {"x": 739, "y": 142}, "confidence": 0.11, "topleft": {"x": 691, "y": 58}}, {"label": "person", "bottomright": {"x": 802, "y": 150}, "confidence": 0.16, "topleft": {"x": 760, "y": 44}}, {"label": "person", "bottomright": {"x": 1127, "y": 117}, "confidence": 0.07, "topleft": {"x": 1090, "y": 88}}, {"label": "person", "bottomright": {"x": 1268, "y": 112}, "confidence": 0.09, "topleft": {"x": 1231, "y": 75}}, {"label": "person", "bottomright": {"x": 384, "y": 175}, "confidence": 0.12, "topleft": {"x": 326, "y": 94}}, {"label": "person", "bottomright": {"x": 471, "y": 178}, "confidence": 0.22, "topleft": {"x": 421, "y": 97}}, {"label": "person", "bottomright": {"x": 533, "y": 182}, "confidence": 0.15, "topleft": {"x": 486, "y": 91}}, {"label": "person", "bottomright": {"x": 596, "y": 184}, "confidence": 0.28, "topleft": {"x": 552, "y": 97}}, {"label": "person", "bottomright": {"x": 658, "y": 192}, "confidence": 0.27, "topleft": {"x": 608, "y": 90}}, {"label": "person", "bottomright": {"x": 735, "y": 191}, "confidence": 0.27, "topleft": {"x": 682, "y": 82}}, {"label": "person", "bottomright": {"x": 1238, "y": 253}, "confidence": 0.41, "topleft": {"x": 168, "y": 8}}, {"label": "person", "bottomright": {"x": 800, "y": 192}, "confidence": 0.24, "topleft": {"x": 753, "y": 80}}, {"label": "person", "bottomright": {"x": 857, "y": 154}, "confidence": 0.09, "topleft": {"x": 821, "y": 106}}, {"label": "person", "bottomright": {"x": 925, "y": 156}, "confidence": 0.09, "topleft": {"x": 894, "y": 109}}, {"label": "person", "bottomright": {"x": 991, "y": 158}, "confidence": 0.14, "topleft": {"x": 959, "y": 107}}, {"label": "person", "bottomright": {"x": 988, "y": 182}, "confidence": 0.14, "topleft": {"x": 939, "y": 96}}, {"label": "person", "bottomright": {"x": 1056, "y": 149}, "confidence": 0.1, "topleft": {"x": 1022, "y": 111}}, {"label": "person", "bottomright": {"x": 1130, "y": 147}, "confidence": 0.1, "topleft": {"x": 1093, "y": 111}}, {"label": "person", "bottomright": {"x": 401, "y": 240}, "confidence": 0.22, "topleft": {"x": 339, "y": 115}}, {"label": "person", "bottomright": {"x": 882, "y": 205}, "confidence": 0.35, "topleft": {"x": 829, "y": 116}}, {"label": "person", "bottomright": {"x": 921, "y": 206}, "confidence": 0.25, "topleft": {"x": 871, "y": 116}}, {"label": "person", "bottomright": {"x": 996, "y": 193}, "confidence": 0.07, "topleft": {"x": 968, "y": 139}}, {"label": "person", "bottomright": {"x": 1000, "y": 212}, "confidence": 0.14, "topleft": {"x": 953, "y": 114}}, {"label": "person", "bottomright": {"x": 1053, "y": 196}, "confidence": 0.08, "topleft": {"x": 1024, "y": 143}}, {"label": "person", "bottomright": {"x": 1064, "y": 223}, "confidence": 0.21, "topleft": {"x": 1015, "y": 119}}, {"label": "person", "bottomright": {"x": 325, "y": 257}, "confidence": 0.2, "topleft": {"x": 274, "y": 140}}, {"label": "person", "bottomright": {"x": 1089, "y": 265}, "confidence": 0.09, "topleft": {"x": 1030, "y": 145}}, {"label": "person", "bottomright": {"x": 1137, "y": 267}, "confidence": 0.26, "topleft": {"x": 1074, "y": 131}}, {"label": "person", "bottomright": {"x": 76, "y": 293}, "confidence": 0.06, "topleft": {"x": 11, "y": 189}}, {"label": "person", "bottomright": {"x": 200, "y": 291}, "confidence": 0.06, "topleft": {"x": 132, "y": 194}}, {"label": "person", "bottomright": {"x": 574, "y": 305}, "confidence": 0.31, "topleft": {"x": 513, "y": 193}}, {"label": "person", "bottomright": {"x": 750, "y": 298}, "confidence": 0.22, "topleft": {"x": 686, "y": 212}}, {"label": "person", "bottomright": {"x": 396, "y": 341}, "confidence": 0.46, "topleft": {"x": 343, "y": 215}}, {"label": "person", "bottomright": {"x": 477, "y": 345}, "confidence": 0.52, "topleft": {"x": 422, "y": 226}}, {"label": "person", "bottomright": {"x": 551, "y": 335}, "confidence": 0.06, "topleft": {"x": 489, "y": 216}}, {"label": "person", "bottomright": {"x": 1052, "y": 532}, "confidence": 0.2, "topleft": {"x": 79, "y": 38}}, {"label": "person", "bottomright": {"x": 1221, "y": 404}, "confidence": 0.32, "topleft": {"x": 1173, "y": 225}}, {"label": "person", "bottomright": {"x": 380, "y": 411}, "confidence": 0.25, "topleft": {"x": 306, "y": 296}}, {"label": "person", "bottomright": {"x": 765, "y": 506}, "confidence": 0.55, "topleft": {"x": 671, "y": 220}}, {"label": "person", "bottomright": {"x": 760, "y": 520}, "confidence": 0.35, "topleft": {"x": 695, "y": 349}}, {"label": "person", "bottomright": {"x": 502, "y": 566}, "confidence": 0.09, "topleft": {"x": 434, "y": 454}}, {"label": "person", "bottomright": {"x": 533, "y": 588}, "confidence": 0.26, "topleft": {"x": 467, "y": 448}}, {"label": "person", "bottomright": {"x": 584, "y": 612}, "confidence": 0.1, "topleft": {"x": 442, "y": 432}}, {"label": "person", "bottomright": {"x": 73, "y": 652}, "confidence": 0.55, "topleft": {"x": 8, "y": 528}}, {"label": "person", "bottomright": {"x": 125, "y": 619}, "confidence": 0.11, "topleft": {"x": 92, "y": 578}}, {"label": "person", "bottomright": {"x": 116, "y": 650}, "confidence": 0.21, "topleft": {"x": 78, "y": 592}}, {"label": "person", "bottomright": {"x": 138, "y": 669}, "confidence": 0.25, "topleft": {"x": 86, "y": 584}}, {"label": "person", "bottomright": {"x": 185, "y": 645}, "confidence": 0.11, "topleft": {"x": 147, "y": 600}}, {"label": "person", "bottomright": {"x": 214, "y": 665}, "confidence": 0.3, "topleft": {"x": 150, "y": 587}}, {"label": "person", "bottomright": {"x": 253, "y": 645}, "confidence": 0.27, "topleft": {"x": 213, "y": 600}}, {"label": "person", "bottomright": {"x": 257, "y": 663}, "confidence": 0.09, "topleft": {"x": 186, "y": 597}}, {"label": "person", "bottomright": {"x": 133, "y": 700}, "confidence": 0.08, "topleft": {"x": 72, "y": 617}}, {"label": "person", "bottomright": {"x": 209, "y": 700}, "confidence": 0.08, "topleft": {"x": 144, "y": 620}}, {"label": "person", "bottomright": {"x": 249, "y": 699}, "confidence": 0.11, "topleft": {"x": 193, "y": 627}}, {"label": "person", "bottomright": {"x": 357, "y": 719}, "confidence": 0.08, "topleft": {"x": 260, "y": 665}}, {"label": "person", "bottomright": {"x": 394, "y": 718}, "confidence": 0.21, "topleft": {"x": 322, "y": 660}}, {"label": "person", "bottomright": {"x": 482, "y": 719}, "confidence": 0.29, "topleft": {"x": 395, "y": 659}}, {"label": "person", "bottomright": {"x": 541, "y": 719}, "confidence": 0.11, "topleft": {"x": 452, "y": 665}}, {"label": "person", "bottomright": {"x": 624, "y": 719}, "confidence": 0.11, "topleft": {"x": 524, "y": 665}}, {"label": "person", "bottomright": {"x": 721, "y": 719}, "confidence": 0.18, "topleft": {"x": 650, "y": 661}}, {"label": "person", "bottomright": {"x": 785, "y": 719}, "confidence": 0.37, "topleft": {"x": 715, "y": 659}}, {"label": "person", "bottomright": {"x": 883, "y": 719}, "confidence": 0.29, "topleft": {"x": 809, "y": 666}}, {"label": "person", "bottomright": {"x": 927, "y": 713}, "confidence": 0.12, "topleft": {"x": 890, "y": 680}}, {"label": "person", "bottomright": {"x": 959, "y": 719}, "confidence": 0.09, "topleft": {"x": 876, "y": 670}}, {"label": "person", "bottomright": {"x": 996, "y": 714}, "confidence": 0.07, "topleft": {"x": 947, "y": 682}}, {"label": "person", "bottomright": {"x": 1007, "y": 719}, "confidence": 0.36, "topleft": {"x": 918, "y": 670}}, {"label": "person", "bottomright": {"x": 1052, "y": 719}, "confidence": 0.23, "topleft": {"x": 1010, "y": 695}}, {"label": "person", "bottomright": {"x": 1148, "y": 719}, "confidence": 0.38, "topleft": {"x": 1050, "y": 677}}, {"label": "person", "bottomright": {"x": 1215, "y": 719}, "confidence": 0.08, "topleft": {"x": 1171, "y": 708}}, {"label": "person", "bottomright": {"x": 1268, "y": 719}, "confidence": 0.08, "topleft": {"x": 1240, "y": 701}}]