[{"topleft": {"x": 736, "y": 109}, "label": "person", "confidence": 0.33, "bottomright": {"x": 781, "y": 218}}, {"topleft": {"x": 876, "y": 111}, "label": "person", "confidence": 0.5, "bottomright": {"x": 930, "y": 240}}, {"topleft": {"x": 1019, "y": 112}, "label": "person", "confidence": 0.3, "bottomright": {"x": 1073, "y": 238}}, {"topleft": {"x": 52, "y": 152}, "label": "person", "confidence": 0.53, "bottomright": {"x": 114, "y": 269}}, {"topleft": {"x": 222, "y": 141}, "label": "person", "confidence": 0.52, "bottomright": {"x": 279, "y": 272}}, {"topleft": {"x": 781, "y": 146}, "label": "person", "confidence": 0.49, "bottomright": {"x": 862, "y": 274}}, {"topleft": {"x": 563, "y": 202}, "label": "person", "confidence": 0.54, "bottomright": {"x": 625, "y": 349}}, {"topleft": {"x": 895, "y": 212}, "label": "person", "confidence": 0.6, "bottomright": {"x": 953, "y": 371}}, {"topleft": {"x": 292, "y": 244}, "label": "person", "confidence": 0.64, "bottomright": {"x": 350, "y": 424}}, {"topleft": {"x": 406, "y": 215}, "label": "person", "confidence": 0.81, "bottomright": {"x": 494, "y": 443}}, {"topleft": {"x": 711, "y": 211}, "label": "person", "confidence": 0.49, "bottomright": {"x": 827, "y": 430}}, {"topleft": {"x": 1140, "y": 244}, "label": "person", "confidence": 0.7, "bottomright": {"x": 1222, "y": 451}}, {"topleft": {"x": 20, "y": 309}, "label": "person", "confidence": 0.68, "bottomright": {"x": 135, "y": 546}}, {"topleft": {"x": 568, "y": 389}, "label": "person", "confidence": 0.56, "bottomright": {"x": 677, "y": 604}}, {"topleft": {"x": 48, "y": 612}, "label": "person", "confidence": 0.33, "bottomright": {"x": 134, "y": 719}}]