[{"topleft": {"y": 192, "x": 544}, "bottomright": {"y": 293, "x": 589}, "confidence": 0.06, "label": "person"}, {"topleft": {"y": 198, "x": 956}, "bottomright": {"y": 300, "x": 999}, "confidence": 0.4, "label": "person"}, {"topleft": {"y": 189, "x": 1079}, "bottomright": {"y": 315, "x": 1124}, "confidence": 0.32, "label": "person"}, {"topleft": {"y": 230, "x": 195}, "bottomright": {"y": 340, "x": 253}, "confidence": 0.38, "label": "person"}, {"topleft": {"y": 200, "x": 591}, "bottomright": {"y": 361, "x": 653}, "confidence": 0.55, "label": "person"}, {"topleft": {"y": 223, "x": 1091}, "bottomright": {"y": 328, "x": 1143}, "confidence": 0.13, "label": "person"}, {"topleft": {"y": 217, "x": 1140}, "bottomright": {"y": 345, "x": 1191}, "confidence": 0.21, "label": "person"}, {"topleft": {"y": 209, "x": 345}, "bottomright": {"y": 438, "x": 427}, "confidence": 0.09, "label": "person"}, {"topleft": {"y": 208, "x": 388}, "bottomright": {"y": 454, "x": 486}, "confidence": 0.51, "label": "person"}, {"topleft": {"y": 230, "x": 706}, "bottomright": {"y": 397, "x": 763}, "confidence": 0.46, "label": "person"}, {"topleft": {"y": 240, "x": 1175}, "bottomright": {"y": 396, "x": 1258}, "confidence": 0.66, "label": "person"}, {"topleft": {"y": 290, "x": 365}, "bottomright": {"y": 437, "x": 415}, "confidence": 0.43, "label": "person"}, {"topleft": {"y": 258, "x": 445}, "bottomright": {"y": 456, "x": 573}, "confidence": 0.41, "label": "person"}, {"topleft": {"y": 282, "x": 514}, "bottomright": {"y": 431, "x": 577}, "confidence": 0.36, "label": "person"}, {"topleft": {"y": 347, "x": 3}, "bottomright": {"y": 460, "x": 52}, "confidence": 0.11, "label": "person"}, {"topleft": {"y": 327, "x": 932}, "bottomright": {"y": 495, "x": 997}, "confidence": 0.76, "label": "person"}, {"topleft": {"y": 404, "x": 190}, "bottomright": {"y": 617, "x": 289}, "confidence": 0.43, "label": "person"}, {"topleft": {"y": 456, "x": 525}, "bottomright": {"y": 592, "x": 592}, "confidence": 0.42, "label": "person"}, {"topleft": {"y": 465, "x": 509}, "bottomright": {"y": 695, "x": 606}, "confidence": 0.15, "label": "person"}, {"topleft": {"y": 616, "x": 7}, "bottomright": {"y": 718, "x": 76}, "confidence": 0.23, "label": "person"}, {"topleft": {"y": 614, "x": 79}, "bottomright": {"y": 719, "x": 137}, "confidence": 0.13, "label": "person"}]