[{"topleft": {"y": 86, "x": 618}, "bottomright": {"y": 194, "x": 657}, "confidence": 0.32, "label": "person"}, {"topleft": {"y": 84, "x": 677}, "bottomright": {"y": 189, "x": 723}, "confidence": 0.23, "label": "person"}, {"topleft": {"y": 78, "x": 877}, "bottomright": {"y": 198, "x": 927}, "confidence": 0.27, "label": "person"}, {"topleft": {"y": 114, "x": 1013}, "bottomright": {"y": 236, "x": 1053}, "confidence": 0.36, "label": "person"}, {"topleft": {"y": 119, "x": 1068}, "bottomright": {"y": 230, "x": 1117}, "confidence": 0.23, "label": "person"}, {"topleft": {"y": 155, "x": 77}, "bottomright": {"y": 263, "x": 149}, "confidence": 0.38, "label": "person"}, {"topleft": {"y": 175, "x": 603}, "bottomright": {"y": 338, "x": 680}, "confidence": 0.66, "label": "person"}, {"topleft": {"y": 156, "x": 948}, "bottomright": {"y": 339, "x": 995}, "confidence": 0.43, "label": "person"}, {"topleft": {"y": 129, "x": 1109}, "bottomright": {"y": 343, "x": 1201}, "confidence": 0.55, "label": "person"}, {"topleft": {"y": 229, "x": 272}, "bottomright": {"y": 343, "x": 364}, "confidence": 0.08, "label": "person"}, {"topleft": {"y": 210, "x": 311}, "bottomright": {"y": 369, "x": 390}, "confidence": 0.65, "label": "person"}, {"topleft": {"y": 209, "x": 452}, "bottomright": {"y": 365, "x": 518}, "confidence": 0.72, "label": "person"}, {"topleft": {"y": 229, "x": 7}, "bottomright": {"y": 394, "x": 80}, "confidence": 0.24, "label": "person"}, {"topleft": {"y": 209, "x": 721}, "bottomright": {"y": 434, "x": 808}, "confidence": 0.8, "label": "person"}, {"topleft": {"y": 267, "x": 187}, "bottomright": {"y": 507, "x": 293}, "confidence": 0.57, "label": "person"}, {"topleft": {"y": 305, "x": 530}, "bottomright": {"y": 506, "x": 639}, "confidence": 0.76, "label": "person"}, {"topleft": {"y": 386, "x": 882}, "bottomright": {"y": 610, "x": 965}, "confidence": 0.76, "label": "person"}, {"topleft": {"y": 533, "x": 5}, "bottomright": {"y": 660, "x": 65}, "confidence": 0.27, "label": "person"}, {"topleft": {"y": 565, "x": 457}, "bottomright": {"y": 692, "x": 526}, "confidence": 0.16, "label": "person"}, {"topleft": {"y": 605, "x": 15}, "bottomright": {"y": 706, "x": 95}, "confidence": 0.16, "label": "person"}, {"topleft": {"y": 595, "x": 78}, "bottomright": {"y": 719, "x": 161}, "confidence": 0.25, "label": "person"}, {"topleft": {"y": 606, "x": 148}, "bottomright": {"y": 719, "x": 222}, "confidence": 0.2, "label": "person"}]