[{"topleft": {"y": 84, "x": 621}, "bottomright": {"y": 196, "x": 659}, "confidence": 0.15, "label": "person"}, {"topleft": {"y": 121, "x": 494}, "bottomright": {"y": 231, "x": 536}, "confidence": 0.57, "label": "person"}, {"topleft": {"y": 124, "x": 947}, "bottomright": {"y": 226, "x": 993}, "confidence": 0.08, "label": "person"}, {"topleft": {"y": 112, "x": 1028}, "bottomright": {"y": 238, "x": 1072}, "confidence": 0.2, "label": "person"}, {"topleft": {"y": 124, "x": 1081}, "bottomright": {"y": 230, "x": 1137}, "confidence": 0.18, "label": "person"}, {"topleft": {"y": 150, "x": 98}, "bottomright": {"y": 270, "x": 152}, "confidence": 0.29, "label": "person"}, {"topleft": {"y": 144, "x": 121}, "bottomright": {"y": 267, "x": 186}, "confidence": 0.51, "label": "person"}, {"topleft": {"y": 126, "x": 295}, "bottomright": {"y": 272, "x": 359}, "confidence": 0.65, "label": "person"}, {"topleft": {"y": 147, "x": 328}, "bottomright": {"y": 262, "x": 392}, "confidence": 0.12, "label": "person"}, {"topleft": {"y": 132, "x": 795}, "bottomright": {"y": 274, "x": 865}, "confidence": 0.49, "label": "person"}, {"topleft": {"y": 122, "x": 895}, "bottomright": {"y": 269, "x": 954}, "confidence": 0.47, "label": "person"}, {"topleft": {"y": 229, "x": 343}, "bottomright": {"y": 346, "x": 400}, "confidence": 0.06, "label": "person"}, {"topleft": {"y": 217, "x": 699}, "bottomright": {"y": 368, "x": 757}, "confidence": 0.5, "label": "person"}, {"topleft": {"y": 258, "x": 301}, "bottomright": {"y": 407, "x": 364}, "confidence": 0.43, "label": "person"}, {"topleft": {"y": 208, "x": 315}, "bottomright": {"y": 424, "x": 413}, "confidence": 0.34, "label": "person"}, {"topleft": {"y": 193, "x": 381}, "bottomright": {"y": 423, "x": 470}, "confidence": 0.74, "label": "person"}, {"topleft": {"y": 209, "x": 667}, "bottomright": {"y": 414, "x": 781}, "confidence": 0.08, "label": "person"}, {"topleft": {"y": 248, "x": 980}, "bottomright": {"y": 380, "x": 1027}, "confidence": 0.57, "label": "person"}, {"topleft": {"y": 246, "x": 1195}, "bottomright": {"y": 459, "x": 1271}, "confidence": 0.57, "label": "person"}, {"topleft": {"y": 321, "x": 84}, "bottomright": {"y": 500, "x": 154}, "confidence": 0.51, "label": "person"}, {"topleft": {"y": 391, "x": 498}, "bottomright": {"y": 493, "x": 566}, "confidence": 0.15, "label": "person"}, {"topleft": {"y": 364, "x": 504}, "bottomright": {"y": 586, "x": 589}, "confidence": 0.66, "label": "person"}, {"topleft": {"y": 563, "x": 5}, "bottomright": {"y": 683, "x": 64}, "confidence": 0.05, "label": "person"}, {"topleft": {"y": 564, "x": 255}, "bottomright": {"y": 685, "x": 331}, "confidence": 0.06, "label": "person"}]