[{"confidence": 0.15, "topleft": {"x": 0, "y": 167}, "bottomright": {"x": 40, "y": 329}, "label": "person"}, {"confidence": 0.3, "topleft": {"x": 384, "y": 250}, "bottomright": {"x": 459, "y": 402}, "label": "person"}, {"confidence": 0.57, "topleft": {"x": 297, "y": 287}, "bottomright": {"x": 365, "y": 444}, "label": "person"}, {"confidence": 0.08, "topleft": {"x": 627, "y": 287}, "bottomright": {"x": 697, "y": 420}, "label": "person"}, {"confidence": 0.39, "topleft": {"x": 682, "y": 268}, "bottomright": {"x": 748, "y": 428}, "label": "person"}, {"confidence": 0.26, "topleft": {"x": 713, "y": 286}, "bottomright": {"x": 784, "y": 429}, "label": "person"}, {"confidence": 0.11, "topleft": {"x": 689, "y": 262}, "bottomright": {"x": 824, "y": 455}, "label": "person"}, {"confidence": 0.46, "topleft": {"x": 722, "y": 405}, "bottomright": {"x": 817, "y": 561}, "label": "person"}, {"confidence": 0.55, "topleft": {"x": 800, "y": 422}, "bottomright": {"x": 932, "y": 601}, "label": "person"}]