[{"label": "person", "bottomright": {"y": 261, "x": 1233}, "confidence": 0.53, "topleft": {"y": 1, "x": 186}}, {"label": "person", "bottomright": {"y": 231, "x": 536}, "confidence": 0.57, "topleft": {"y": 121, "x": 494}}, {"label": "person", "bottomright": {"y": 267, "x": 186}, "confidence": 0.51, "topleft": {"y": 144, "x": 121}}, {"label": "person", "bottomright": {"y": 272, "x": 359}, "confidence": 0.65, "topleft": {"y": 126, "x": 295}}, {"label": "person", "bottomright": {"y": 423, "x": 470}, "confidence": 0.74, "topleft": {"y": 193, "x": 381}}, {"label": "person", "bottomright": {"y": 380, "x": 1027}, "confidence": 0.57, "topleft": {"y": 248, "x": 980}}, {"label": "person", "bottomright": {"y": 459, "x": 1271}, "confidence": 0.57, "topleft": {"y": 246, "x": 1195}}, {"label": "person", "bottomright": {"y": 500, "x": 154}, "confidence": 0.51, "topleft": {"y": 321, "x": 84}}, {"label": "person", "bottomright": {"y": 586, "x": 589}, "confidence": 0.66, "topleft": {"y": 364, "x": 504}}, {"label": "person", "bottomright": {"y": 719, "x": 1132}, "confidence": 0.56, "topleft": {"y": 625, "x": 1052}}, {"label": "person", "bottomright": {"y": 715, "x": 1202}, "confidence": 0.52, "topleft": {"y": 641, "x": 1132}}, {"label": "person", "bottomright": {"y": 719, "x": 1258}, "confidence": 0.65, "topleft": {"y": 660, "x": 1190}}]